fntypes/__init__.py
fntypes/co.py
fntypes/error.py
fntypes/lazy.py
fntypes/lazy_coro.py
fntypes/lazy_coro_result.py
fntypes/misc.py
fntypes/option.py
fntypes/py.typed
fntypes/result/__init__.py
fntypes/result/log_factory.py
fntypes/result/result.py
fntypes/tools/__init__.py
fntypes/tools/caching.py
fntypes/tools/runtime_generic.py
fntypes/tools/singleton.py
fntypes/tools/unwrapping.py
fntypes/variative.py
funtypes-0.2.1.dist-info/METADATA
funtypes-0.2.1.dist-info/WHEEL
funtypes-0.2.1.dist-info/RECORD
