Metadata-Version: 2.3
Name: funtypes
Version: 0.2.1
Summary: FUNctional types for Python. (Backport to 0.2.1)
Author: luwqz1
Author-email: howluwqz1@gmail.com
Maintainer: luwqz1
Maintainer-email: howluwqz1@gmail.com
Requires-Python: >=3.12,<4.0
Classifier: Programming Language :: Python :: 3
Classifier: Programming Language :: Python :: 3.12
Classifier: Programming Language :: Python :: 3.13
Requires-Dist: typing-extensions (>=4.14.0,<5.0.0)
